[{"originalPostURL":"https://showerthoughtsofficial.tumblr.com/post/173794856378","postBodyContent":"\n                                                                        <p>slow wifi is somehow more frustrating than no wifi</p>\n                                                                    ","rebloggedPostURL":"https://getbacktofandomlife.tumblr.com/post/715794970440777728/charlesoberonn-showerthoughtsofficial-slow"},{"originalPostURL":"https://willowrosenboob.tumblr.com/post/661349356826476544","postBodyContent":"\n                                                                    <p><small>BTVS 3.22<br><i>Take a moment to deal with this. We survived.<br>It was a hell of a battle.<br>Not the battle. High school.</i></small></p>\n                                                                ","rebloggedPostURL":"https://getbacktofandomlife.tumblr.com/post/715794967652663296/willowrosenboob-btvs-322-take-a-moment-to-deal"},{"originalPostURL":"https://yassmines.tumblr.com/post/647833437144776704","postBodyContent":"\n                                                                        <p>my favorite part abt this generation is no one is ironing their clothes anymore fjckfncn fuck that! if the wrinkles wanna be there let them</p>\n                                                                    ","rebloggedPostURL":"https://getbacktofandomlife.tumblr.com/post/715794962107826176"},{"originalPostURL":"https://starlightcastiel.tumblr.com/post/660147025734696960","postBodyContent":"\n                                                                    <p></p><p><small><b>spncreatorsdaily 2k celebration | day 6: locations</b></small></p><blockquote><div><small><b><span style=\"color:#447294\">d</span><span style=\"color:#497894\">e</span><span style=\"color:#4d7d93\">a</span><span style=\"color:#528393\">n</span><span style=\"color:#568893\">c</span><span style=\"color:#5b8e93\">a</span><span style=\"color:#5f9392\">s</span><span style=\"color:#649992\"> </span><span style=\"color:#689e92\">i</span><span style=\"color:#6da492\">n</span><span style=\"color:#71a991\"> </span><span style=\"color:#76af91\">p</span><span style=\"color:#7ab491\">u</span><span style=\"color:#7fba91\">r</span><span style=\"color:#83bf90\">g</span><span style=\"color:#88c590\">a</span><span style=\"color:#8cca90\">t</span><span style=\"color:#91d090\">o</span><span style=\"color:#95d58f\">r</span><span style=\"color:#9adb8f\">y</span></b></small></div></blockquote>\n                                                                ","rebloggedPostURL":"https://getbacktofandomlife.tumblr.com/post/715794959348957184/starlightcastiel-spncreatorsdaily-2k-celebration"},{"originalPostURL":"https://casketbound.tumblr.com/post/168909762293","postBodyContent":"\n                                                                    <p><a href=\"https://href.li/?https://www.flickr.com/photos/sams_stone/\">Sam Stone</a></p>\n                                                                ","rebloggedPostURL":"https://getbacktofandomlife.tumblr.com/post/715794953778921472/casketbound-sam-stone"},{"originalPostURL":"https://tina-snow.tumblr.com/post/659266697388343296","postBodyContent":"\n                                                                    <p><b>LIL NAS X</b><br>Variety Cover Shoot</p>\n                                                                ","rebloggedPostURL":"https://getbacktofandomlife.tumblr.com/post/715794951027474432/tina-snow-lil-nas-x-variety-cover-shoot"},{"originalPostURL":"https://monarchmish.tumblr.com/post/162392793328","postBodyContent":"\n                                                                    <p>Made these in honor of pride month!&nbsp;</p><p>Edit: Added even more flags here —–&gt; [<a href=\"http://monarchmish.tumblr.com/post/162481502713/even-more-flags-stay-proud-friends-1st-post\">2nd Post</a>]</p>\n                                                                ","rebloggedPostURL":"https://getbacktofandomlife.tumblr.com/post/715794948248715264/monarchmish-made-these-in-honor-of-pride"},{"originalPostUsername":"","postBodyContent":"","rebloggedPostURL":"https://getbacktofandomlife.tumblr.com/post/715794945489993728"},{"originalPostUsername":"","postBodyContent":"","rebloggedPostURL":"https://getbacktofandomlife.tumblr.com/post/715794942703878144"},{"originalPostURL":"https://aidashakur.tumblr.com/post/646873355599953920","postBodyContent":"\n                                                                        <p>Be the reason people still believe in kind hearts, authentic vibes and warm souls.</p>\n                                                                    ","rebloggedPostURL":"https://getbacktofandomlife.tumblr.com/post/715794939974402048"}]