[{"originalPostURL":"https://alexanderhamllton.tumblr.com/post/151302411989","postBodyContent":"\n                                                                    <p></p><p><small><a href=\"http://rihleymatthews.tumblr.com/tagged/eml\">endless movie list</a> |&nbsp;<b>moana</b>&nbsp;<i>(2016)</i></small></p><blockquote><p><small><i>\nDo you who Maui is? The greatest demigod that ever lived, who stopped the sun, who pulled up islands out of the sea, and battled monsters. Do you know why I know all this? That’s because I am Maui!\n<br></i></small></p></blockquote>\n                                                                ","rebloggedPostURL":"https://getbacktofandomlife.tumblr.com/post/719508775035420672/alexanderhamllton-endless-movie-list"},{"originalPostURL":"https://jamespottuh.tumblr.com/post/155277757040","postBodyContent":"\n                                                                    <p></p><p><b><a href=\"https://hpwocnetwork.tumblr.com/\">hp woc</a>&nbsp;/&nbsp;<a href=\"http://jamespottuh.tumblr.com/tagged/zay-does-moodboards\">moodboards</a>:</b> hermione jean granger (promo for <a class=\"tumblelog\" href=\"https://tmblr.co/mxpX9Oi4OOVmNTtgwnk197Q\">@hpwocnetwork</a>)</p><blockquote><p><i>“I mean, you could claim that anything’s real if the only basis for believing in it is that nobody’s proved it doesn’t exist!”&nbsp;</i><br></p></blockquote>\n                                                                ","rebloggedPostURL":"https://getbacktofandomlife.tumblr.com/post/719508693159493632/jamespottuh-hp-woc-moodboards-hermione-jean"},{"originalPostUsername":"","postBodyContent":"","rebloggedPostURL":"https://getbacktofandomlife.tumblr.com/post/719508689467408384/i-am-unmade-in-a-torrent-of-glittering-rain"},{"originalPostUsername":"","postBodyContent":"","rebloggedPostURL":"https://getbacktofandomlife.tumblr.com/post/719508687279063040"},{"originalPostURL":"https://norman-reedus.tumblr.com/post/125173574126","postBodyContent":"\n                                                                    <p><small><b><a href=\"http://lydiamarlin.tumblr.com/tagged/mmc3\">make me choose</a></b> → anonymous said: <b>sciles</b> or allydia?<br>“I seriously don’t understand how you survive without me sometimes.” \n\n</small><br></p>\n                                                                ","rebloggedPostURL":"https://getbacktofandomlife.tumblr.com/post/719508243415793664/norman-reedus-make-me-choose-anonymous-said"},{"originalPostURL":"https://pakistaniboyfriend.tumblr.com/post/89064492579","postBodyContent":"\n                                                                    <p></p><h5><em>a pjo/hoo infographic </em>(<a href=\"https://href.li/?http://roseoftyrell.co.vu/post/88238136794\">insp</a>) (<a href=\"https://href.li/?http://roseoftyrell.co.vu/post/79861389261\">x</a>) (<a href=\"http://viria.tumblr.com/\">x</a>) (x) (<a href=\"http://olympusdaily.tumblr.com/post/64796129205\">x</a>)</h5>\n                                                                ","rebloggedPostURL":"https://getbacktofandomlife.tumblr.com/post/719508239866314752/bisexualies-pakistaniboyfriend-a-pjohoo"},{"originalPostURL":"https://batcii.tumblr.com/post/151076340478","postBodyContent":"\n                                                                    <p>a small harry warm up sketch</p>\n                                                                ","rebloggedPostURL":"https://getbacktofandomlife.tumblr.com/post/719508234855120896/batcii-a-small-harry-warm-up-sketch"},{"originalPostURL":"https://ouijabored.tumblr.com/post/115692679771","postBodyContent":"\n                                                                    <p></p><p><small><a href=\"http://ouijabored.tumblr.com/tagged/zodiacaes\"><b>ZODIAC AESTHETICS</b></a> | pisces</small></p><blockquote><div><small><small>Pisceans tend to withdraw into a dream world where their qualities can bring mental satisfaction and sometimes, fame and financial reward for they are extremely gifted artistically. They are also versatile and intuitive, have quick understanding, observe and listen well, and are receptive to new ideas and atmospheres. All these factors can combine to produce remarkable creativity in literature, music and art. They may count among their gifts mediumistic qualities which can give them a feeling that their best work comes from outside themselves, “Whispered beyond the misted curtains, screening this world from that.”\n\n (<a href=\"https://href.li/?http://www.astrology-online.com/pisces.htm\">x</a>)</small></small></div></blockquote>\n                                                                ","rebloggedPostURL":"https://getbacktofandomlife.tumblr.com/post/719508230645137408/ouijabored-zodiac-aesthetics-pisces-pisceans"},{"originalPostURL":"https://urumiya.tumblr.com/post/113433132667","postBodyContent":"\n                                                                    <p>Lily Evans, magical girl of my heart.<br></p>\n                                                                ","rebloggedPostURL":"https://getbacktofandomlife.tumblr.com/post/719508222652891136/urumiya-lily-evans-magical-girl-of-my-heart"},{"originalPostURL":"https://hellasstrology.tumblr.com/post/155198734497","postBodyContent":"\n                                                                        <p>Physical affection: Aries, Taurus, SCORPIO, Aquarius</p><p>Verbal affection: Cancer, Virgo, Libra</p><p>Neither: Gemini, Sagittarius, Capricorn</p><p>Any type of affection because only they’re so needy: Pisces, Leo</p>\n                                                                    ","rebloggedPostURL":"https://getbacktofandomlife.tumblr.com/post/719508217967869952/the-signs-as-types-of-affection"}]