[{"originalPostURL":"https://niklausxcaroline.tumblr.com/post/160424294671","postBodyContent":"\n                                                                    <p><small><b><a href=\"http://niklausxcaroline.tumblr.com/tagged/gifset%3A-aesthetics\">gifset aesthetic</a></b> = james potter and lily evans ♡ “oh well, he always made a fool of himself whenever lily was around,” said sirius, shrugging. “he couldn’t stop himself showing off whenever he got near her.” <i>(request by&nbsp;<a href=\"https://tmblr.co/mosxCgQL4ziZg7PrHsJp8Ag\">@highladyofdreamcourt</a>)</i><br></small></p>\n                                                                ","rebloggedPostURL":"https://getbacktofandomlife.tumblr.com/post/718243892120764416/niklausxcaroline-gifset-aesthetic-james-potter"},{"originalPostURL":"https://milareadsbooks.tumblr.com/post/124063868705","postBodyContent":"\n                                                                        <p>“I Own It But I Haven’t&nbsp;Read It” a story by me<br></p>\n                                                                    ","rebloggedPostURL":"https://getbacktofandomlife.tumblr.com/post/718243889442635776/milareadsbooks-i-own-it-but-i-havent-read-it"},{"originalPostURL":"https://amysartiago.tumblr.com/post/159580649071","postBodyContent":"\n                                                                    <p></p><p><small><b><i>BROOKLYN NINE-NINE</i></b><br></small></p><blockquote><p><small>Captain, hey! Welcome to the<i> </i>murder.<br></small></p></blockquote>\n                                                                ","rebloggedPostURL":"https://getbacktofandomlife.tumblr.com/post/718243886697463808/amysartiago-brooklyn-nine-nine-captain-hey"},{"originalPostURL":"https://escasun.tumblr.com/post/152178501656","postBodyContent":"\n                                                                        <p>me: stutters out fifteen sentence fragments that no-one can make sense of not even me<br>\nme: you know?</p>\n                                                                    ","rebloggedPostURL":"https://getbacktofandomlife.tumblr.com/post/718243883995332608/kasindrarules-escasun-me-stutters-out-fifteen"},{"originalPostURL":"https://odeysseus.tumblr.com/post/158074963352","postBodyContent":"\n                                                                    <p><b>divide&nbsp;</b>: <a href=\"http://odeysseus.tumblr.com/divide\">preview</a> / <a href=\"https://href.li/?http://pastebin.com/ZVSWL8nr\">download</a></p><p>three guesses what this was inspired by…! it’s a simple tags page with four columns, tag boxes are stacked using masonry. it’s fairly easy to customise and all editing instructions are in the code.&nbsp;</p>\n                                                                ","rebloggedPostURL":"https://getbacktofandomlife.tumblr.com/post/718243881293168640/odeysseus-divide-preview-download-three"},{"originalPostURL":"https://yay4hamlet.tumblr.com/post/160688265087","postBodyContent":"\n                                                                    <p>who gave her the right to be so perfect</p>\n                                                                ","rebloggedPostURL":"https://getbacktofandomlife.tumblr.com/post/718243878610796544/yay4hamlet-who-gave-her-the-right-to-be-so"},{"originalPostURL":"https://tfa.tumblr.com/post/160670783385","postBodyContent":"\n                                                                    <p><small>I fear nothing. For all is as the Force wills it.</small></p>\n                                                                ","rebloggedPostURL":"https://getbacktofandomlife.tumblr.com/post/718243875927588864/tfa-i-fear-nothing-for-all-is-as-the-force-wills"},{"originalPostURL":"https://bisummers.tumblr.com/post/160673424040","postBodyContent":"\n                                                                    <p><a href=\"http://tattooeyes.tumblr.com/tagged/btvs-cast\">racebent&nbsp;btvs </a>&nbsp;+ <a href=\"http://tattooeyes.tumblr.com/tagged/btvs-insta\">instagram</a> | <i>somali tara &amp; malaysian&nbsp;willow</i></p>\n                                                                ","rebloggedPostURL":"https://getbacktofandomlife.tumblr.com/post/718243873284128768/bisummers-racebent-btvs-instagram-somali"},{"originalPostURL":"https://soph-okonedo.tumblr.com/post/160696498974","postBodyContent":"\n                                                                    <p>Zoe Kravitz for ALLURE Magazine June 2017</p>\n                                                                ","rebloggedPostURL":"https://getbacktofandomlife.tumblr.com/post/718243870569283584/soph-okonedo-zoe-kravitz-for-allure-magazine-june"},{"originalPostURL":"https://odeysseus.tumblr.com/post/147141965752","postBodyContent":"\n                                                                    <p><b>peppermint </b>: <a href=\"http://odeysseus.tumblr.com/bookshelf\">preview</a> / <a href=\"https://href.li/?http://pastebin.com/QrCY9BAr\">download</a></p><p>a bookshelf page - finally! this page can be used to showcase book or fic recs and has space for the name, author, a description, a link to the book’s goodreads (or a link to the fic) and a star rating; there are instructions in the code for basic customisation as well as editing books and filters.&nbsp;</p>\n                                                                ","rebloggedPostURL":"https://getbacktofandomlife.tumblr.com/post/718243867889156096/odeysseus-peppermint-preview-download-a"}]