[{"originalPostURL":"https://cophines.tumblr.com/post/180480462910","postBodyContent":"\n                                                                    <p></p><blockquote><p><small><i>It’s kids like us who’ve been through more than other kids. We’re tougher than other kids. We’re really good builders. We make ourselves really safe. And no one ever gets in.</i></small></p></blockquote>\n                                                                ","rebloggedPostURL":"https://getbacktofandomlife.tumblr.com/post/717247093780201472/cophines-its-kids-like-us-whove-been-through"},{"originalPostUsername":"","postBodyContent":"","rebloggedPostURL":"https://getbacktofandomlife.tumblr.com/post/717247091061178368"},{"originalPostURL":"https://discgirl.tumblr.com/post/161040499634","postBodyContent":"\n                                                                    <p></p><blockquote><p><small>\n\nYou think you know what’s to come, what you are. You haven’t even begun.\n\n<br></small></p></blockquote>\n                                                                ","rebloggedPostURL":"https://getbacktofandomlife.tumblr.com/post/717247088342302721/discgirl-you-think-you-know-whats-to-come"},{"originalPostURL":"https://brolinjosh.tumblr.com/post/183524477400","postBodyContent":"\n                                                                    <p><small>I’m not what you think I am.\n\n<br></small></p>\n                                                                ","rebloggedPostURL":"https://getbacktofandomlife.tumblr.com/post/717247085647413248/brolinjosh-im-not-what-you-think-i-am"},{"originalPostURL":"https://slayerdaily.tumblr.com/post/183903538401","postBodyContent":"\n                                                                    <p><small>I don’t care. I’ve had enough. I’ve seen enough. I want out. I want it to end. I don’t care anymore.</small></p><p><small><b><span style=\"color: #4383ff\">N</span><span style=\"color: #4683ff\">o</span><span style=\"color: #4a84ff\">,</span><span style=\"color: #4e85ff\"> </span><span style=\"color: #5286ff\">y</span><span style=\"color: #5587ff\">o</span><span style=\"color: #5987ff\">u</span><span style=\"color: #5d88ff\"> </span><span style=\"color: #6189ff\">d</span><span style=\"color: #648aff\">o</span><span style=\"color: #688bff\">n</span><span style=\"color: #6c8bff\">’</span><span style=\"color: #708cff\">t</span><span style=\"color: #748dff\"> </span><span style=\"color: #778eff\">g</span><span style=\"color: #7b8fff\">e</span><span style=\"color: #7f8fff\">t</span><span style=\"color: #8390ff\"> </span><span style=\"color: #8691ff\">i</span><span style=\"color: #8a92ff\">t</span><span style=\"color: #8e93ff\">.</span><span style=\"color: #9293ff\"> </span><span style=\"color: #9594ff\">I</span><span style=\"color: #9995ff\"> </span><span style=\"color: #9d96ff\">d</span><span style=\"color: #a197ff\">o</span><span style=\"color: #a597ff\">n</span><span style=\"color: #a898ff\">’</span><span style=\"color: #ac99ff\">t</span><span style=\"color: #b09aff\"> </span><span style=\"color: #b49bff\">c</span><span style=\"color: #b79bff\">a</span><span style=\"color: #bb9cff\">r</span><span style=\"color: #bf9dff\">e</span><span style=\"color: #c39eff\">.</span></b></small></p>\n                                                                ","rebloggedPostURL":"https://getbacktofandomlife.tumblr.com/post/717247082959896576/slayerdaily-i-dont-care-ive-had-enough-ive"},{"originalPostURL":"https://calormen.tumblr.com/post/183695575763","postBodyContent":"\n                                                                    <p><small> &nbsp; &nbsp; &nbsp; &nbsp; &nbsp; &nbsp; &nbsp; &nbsp; &nbsp; &nbsp; &nbsp; &nbsp; &nbsp; &nbsp; &nbsp; &nbsp; &nbsp; &nbsp; &nbsp; &nbsp; &nbsp; &nbsp; &nbsp; &nbsp;<b><a href=\"https://calormen.tumblr.com/post/177839593753/narnia-31-day-challenge-below-the-cut-is-31-days\">THE 31 DAY NARNIA CHALLENGE.</a></b><br>&nbsp; &nbsp; &nbsp; &nbsp; &nbsp; &nbsp; &nbsp; &nbsp; &nbsp; &nbsp; &nbsp; &nbsp; &nbsp; &nbsp; &nbsp; &nbsp; &nbsp; &nbsp; &nbsp; &nbsp; &nbsp; &nbsp; &nbsp; &nbsp; &nbsp; &nbsp; &nbsp;<i>day 3: favourite male character.</i></small></p><hr><p><small><i><b>&nbsp; &nbsp; &nbsp; &nbsp; &nbsp; &nbsp; &nbsp; &nbsp; &nbsp; &nbsp; &nbsp; &nbsp; &nbsp; &nbsp; &nbsp; &nbsp; &nbsp; &nbsp; &nbsp; &nbsp; &nbsp; &nbsp; &nbsp; &nbsp; &nbsp; &nbsp;</b>&nbsp;king <b>edmund</b>, crowned<b> the just.</b><br><b>&nbsp; &nbsp; &nbsp; &nbsp; &nbsp; &nbsp; &nbsp; &nbsp; &nbsp; &nbsp; &nbsp; &nbsp; &nbsp; &nbsp; &nbsp; ‘ </b>but even a traitor may mend. i have known one that did.<b> ’</b><br></i></small></p>\n                                                                ","rebloggedPostURL":"https://getbacktofandomlife.tumblr.com/post/717247080275591168/calormen"},{"originalPostURL":"https://redlipstickresurrected.tumblr.com/post/180941123290","postBodyContent":"\n                                                                    <p>Sue Sareen (British, b. Merseyside, England, based Nottingham, England) - <b>1:</b> Cheerful Cat Rufford&nbsp; <b>2:</b> Sleepy Cat&nbsp; <b>3:</b> Curled Up Cat&nbsp; Drawings</p>\n                                                                ","rebloggedPostURL":"https://getbacktofandomlife.tumblr.com/post/717247077588107264/redlipstickresurrected-sue-sareen-british-b"},{"originalPostURL":"https://hanatsuki89.tumblr.com/post/182697456378","postBodyContent":"\n                                                                    <p>I was thinking about malfoy’s demeaning quote about Ron in the first movie and turned it into something fluffy for these two (you can tell Ron doesn’t know what this is all about in the third panel, lol)<br><br>Let these boys hug more 2k19</p>\n                                                                ","rebloggedPostURL":"https://getbacktofandomlife.tumblr.com/post/717247074917351424/hanatsuki89-i-was-thinking-about-malfoys"},{"originalPostUsername":"softlywlw","postBodyContent":"\n                                                                        <p>do you ever want a girl to grab you and kiss you so passionately you forget your own name because same </p>\n                                                                    ","rebloggedPostURL":"https://getbacktofandomlife.tumblr.com/post/717247072229900288/do-you-ever-want-a-girl-to-grab-you-and-kiss-you"},{"originalPostURL":"https://belcourtcamille.tumblr.com/post/183566338086","postBodyContent":"\n                                                                    <p></p><p><b><a href=\"https://tmblr.co/m51AyUK3SxKd0hVQy1pDIzA\">@hogwartsonline</a> march quidditch:</b> hermione granger</p><blockquote><p><i>“ooh, you look much tastier than crabbe and goyle, harry\" said hermione, before catching sight of ron’s raised eyebrows, blushing slightly and saying “oh you know what I mean - goyle’s potion looked like bogies.” \n\n</i><br></p></blockquote>\n                                                                ","rebloggedPostURL":"https://getbacktofandomlife.tumblr.com/post/717247052435865600/belcourtcamille-hogwartsonline-march-quidditch"}]