[{"originalPostURL":"https://bioships.tumblr.com/post/142157507205","postBodyContent":"\n                                                                    <p></p><blockquote><p><small>luke skywalker? i thought he was a myth.</small></p></blockquote>\n                                                                ","rebloggedPostURL":"https://getbacktofandomlife.tumblr.com/post/719225829532532736/bioships-luke-skywalker-i-thought-he-was-a"},{"originalPostURL":"https://cascadians.tumblr.com/post/52630348573","postBodyContent":"\n                                                                        <p>i don’t think anyone understands that when i say i get secondhand embarrassment easily i mean at the first sign of trouble for a character in a television show i immediately pause and sit there for ten to thirty minutes thinking “oh god they fucked up”</p>\n                                                                    ","rebloggedPostURL":"https://getbacktofandomlife.tumblr.com/post/719225826825125888/cascadians-i-dont-think-anyone-understands-that"},{"originalPostURL":"https://eleadore.tumblr.com/post/147451287431","postBodyContent":"\n                                                                    <p>little prince&nbsp;🐉</p><p><a href=\"http://eleadore.tumblr.com/post/146968972276/boy-wonder\">harry</a> |</p>\n                                                                ","rebloggedPostURL":"https://getbacktofandomlife.tumblr.com/post/719225821337927680/eleadore-little-prince-harry"},{"originalPostURL":"https://evanrsiers.tumblr.com/post/147695371035","postBodyContent":"\n                                                                    <p></p><p><sup><a href=\"http://evanrsiers.tumblr.com/tagged/mbedit\">MOODBOARD</a> <b>– &nbsp;Lily Evans</b></sup></p><blockquote><p><sup><i>All that could be seen of Lily Evans was a blur, her bright red hair flying behind her, the movement making it seem like flames. (<a href=\"http://t.umblr.com/redirect?z=https%3A%2F%2Fwww.fanfiction.net%2Fs%2F8208907%2F1%2FThe-Tale-of-Lily-Evans&amp;t=ZTcxZDNjY2VmMWQ0ZTliMGI2MjhiNDY4YTBkMGMzYjBhYjAzMDNmYyxkR2J3Vkx3dw%3D%3D\">x</a>)</i>&nbsp;<b><br></b></sup></p></blockquote>\n                                                                ","rebloggedPostURL":"https://getbacktofandomlife.tumblr.com/post/719225818490994688/evanrsiers-moodboard-lily-evans-all-that"},{"originalPostURL":"https://ceruleanvulpine.tumblr.com/post/140947651293","postBodyContent":"\n                                                                        <p>ALSO I’m now just f a s c i n a t e d by the interplay of narrator-burr, looking back on his actions with some regret, and in-the-action burr, convinced what he’s doing is right and necessary… sometimes it gives the impression that he’s getting caught up in the action, becoming invested in events despite part of him being outside and above them. sometimes he’s desperately defending himself, as in The World Was Wide Enough as the duel is getting set up, where he’s /shouting/ - and I mean he sounds /unhinged/ - his Totally Valid Reasons for why shooting Hamilton made sense at the time. and then right after he shoots he slides back into the larger historical perspective!!</p><p>in conclusion leslie odom jr is fucking brilliant and I’m so pleased</p>\n                                                                    ","rebloggedPostURL":"https://getbacktofandomlife.tumblr.com/post/719225815479582720/ceruleanvulpine-also-im-now-just-f-a-s-c-i-n-a"},{"originalPostURL":"https://kyohonda.tumblr.com/post/154540765506","postBodyContent":"\n                                                                    <p></p><blockquote><p><small>and if when everything ends, nothing is left in my hands… that’s alright.</small><br></p></blockquote>\n                                                                ","rebloggedPostURL":"https://getbacktofandomlife.tumblr.com/post/719225811565150208/kyohonda-and-if-when-everything-ends-nothing-is"},{"originalPostUsername":"stimpoweredgiraffe","postBodyContent":"\n                                                                        <p></p><p>things that do romanticize mental illness</p><ul><li>neurotypical people picking and choosing which parts of a mental illness to portray in media and deliberately glossing over the unpleasant parts and struggles neurodivergent people face</li></ul><p>things that do not romanticize mental illness</p><ul><li>neurodivergent people feeling cute and loving themselves</li></ul><ul><li>neurodivergent people posting about how they headcanon their favorite characters as being like them</li></ul>\n                                                                    ","rebloggedPostURL":"https://getbacktofandomlife.tumblr.com/post/719225808979460096/stimpoweredgiraffe-things-that-do-romanticize"},{"originalPostURL":"https://fairyisle.tumblr.com/post/154782448022","postBodyContent":"\n                                                                    <p>The name’s Finn and I’m in charge. I’m in charge now, Phasma. I’m in charge.<br></p>\n                                                                ","rebloggedPostURL":"https://getbacktofandomlife.tumblr.com/post/719225806319222785/fairyisle-the-names-finn-and-im-in-charge-im"},{"originalPostURL":"https://denerims.tumblr.com/post/147931160744","postBodyContent":"\n                                                                    <p><b>west coast</b> [theme 03] by <a href=\"http://denerims.tumblr.com\">denerims</a><br><a href=\"http://frpreviews.tumblr.com/thm3\">preview</a> - <a href=\"https://href.li/?http://pastebin.com/34ztneyK\">pastebin</a> - <a href=\"http://denerims.tumblr.com/themes\">terms of use</a></p><blockquote><p>Post size, text size, photoset spacing and font options<br>182px sidebar image (auto-adjusts)<br>Five custom links<br>Drop down navigation<br>Hide, hover or static tags<br>Option to change navigation icons</p></blockquote><p>To change the icons for your navigation pick your icon from the list <a href=\"https://href.li/?http://fontawesome.io/icons/\">here</a> and type the keyword (i.e. ‘home’ for a small house instead of ‘fa fa-home’) into the icon text box for that link in your customization options.</p>\n                                                                ","rebloggedPostURL":"https://getbacktofandomlife.tumblr.com/post/719225788432596992/denerims-west-coast-theme-03-by-denerims"},{"originalPostURL":"https://kaladandeqar.tumblr.com/post/153002159206","postBodyContent":"\n                                                                    <p><small><b><i>“Monkey bar,”</i></b> Annabeth said. “I’m great at these.” She leaped onto to the first rung and start swinging her way across. She was scared of tiny spiders, but not of plummeting to her death from a set of monkey bars. Go figure.” </small></p>\n                                                                ","rebloggedPostURL":"https://getbacktofandomlife.tumblr.com/post/719225785072877569/kaladandeqar-monkey-bar-annabeth-said-im"}]