[{"originalPostURL":"https://k2sodone.tumblr.com/post/165935066031","postBodyContent":"\n                                                                    <p></p><p>Tony’s left arm still hurting and trembling after being crushed by a car in Civil War</p><p><br></p><p>Bonus: You can see his helmet showing his injured arm</p><figure><a class=\"post_media_photo_anchor\" data-big-photo=\"https://64.media.tumblr.com/7e38288c9e2bdb668aad12d4c2e43ed3/cd27a84d9011a1ba-d0/s1280x1920/d1fd9f4f051bd9290bcdac9388bee929f5e680ba.gifv\" data-big-photo-height=\"139\" data-big-photo-width=\"268\"><img class=\"post_media_photo image\" src=\"https://64.media.tumblr.com/7e38288c9e2bdb668aad12d4c2e43ed3/cd27a84d9011a1ba-d0/s400x600/6181de24ea866d146b183a3200ca4dfa0a8ec1e7.gifv\" alt=\"image\"></a></figure>\n                                                                ","rebloggedPostURL":"https://getbacktofandomlife.tumblr.com/post/719799137268269056/k2sodone-tonys-left-arm-still-hurting-and"},{"originalPostURL":"https://shirazade.tumblr.com/post/165195992176","postBodyContent":"\n                                                                    <p><small><b>Zoë Kravitz</b> photographed by Hilary Walsh for Tidal Magazine</small><br></p>\n                                                                ","rebloggedPostURL":"https://getbacktofandomlife.tumblr.com/post/719799123839205376/shirazade-zo%C3%AB-kravitz-photographed-by-hilary"},{"originalPostUsername":"skittlesdoesastrology","postBodyContent":"\n                                                                        <p>TAURUS, Cancer, Leo, VIRGO, Scorpio, Sagittarius, CAPRICORN, Pisces</p>\n                                                                    ","rebloggedPostURL":"https://getbacktofandomlife.tumblr.com/post/719799118315274240/internally-dying-all-day-every-day-squad"},{"originalPostUsername":"","postBodyContent":"","rebloggedPostURL":"https://getbacktofandomlife.tumblr.com/post/719799115253497856"},{"originalPostURL":"https://van-dyne.tumblr.com/post/166031025054","postBodyContent":"\n                                                                    <p><small>Iron Man (2008) dir. Jon Favreau</small></p>\n                                                                ","rebloggedPostURL":"https://getbacktofandomlife.tumblr.com/post/719799044826857472/van-dyne-iron-man-2008-dir-jon-favreau"},{"originalPostUsername":"","postBodyContent":"","rebloggedPostURL":"https://getbacktofandomlife.tumblr.com/post/719799029771485184/louis-armstrong-la-vie-en-rose-in-the-rain"},{"originalPostURL":"https://van-dyne.tumblr.com/post/165781407449","postBodyContent":"\n                                                                    <p><small>The suit is holding a supposed glass because Tony is holding one.&nbsp;<br><b>‘The suit and I are one.’ &nbsp;</b>Are they literally going to this direction now 👀<br></small></p>\n                                                                ","rebloggedPostURL":"https://getbacktofandomlife.tumblr.com/post/719799026953977856/van-dyne-van-dyne-the-suit-is-holding-a"},{"originalPostUsername":"","postBodyContent":"\n                                                                    <p>SHIV</p><p>HE THREW A SHIV</p>\n                                                                ","rebloggedPostURL":"https://getbacktofandomlife.tumblr.com/post/719799023654043648/youngsamberg-shiv-he-threw-a-shiv"},{"originalPostURL":"https://munies.tumblr.com/post/165708543827","postBodyContent":"\n                                                                    <p></p><blockquote><p><small><i>. &nbsp; &nbsp; . &nbsp; &nbsp; . &nbsp; &nbsp; tommy</i><b>.</b></small></p></blockquote>\n                                                                ","rebloggedPostURL":"https://getbacktofandomlife.tumblr.com/post/719799017485320192/munies-tommy"},{"originalPostURL":"https://hannahbaker.tumblr.com/post/143548645677","postBodyContent":"\n                                                                    <p><small><b><a href=\"http://lvcasfrlar.tumblr.com/tagged/mmc\">make me choose</a> - </b><i>anon</i> asked:<b>&nbsp;Ravi</b> or <strike>Major</strike>? (iZombie)&nbsp;</small><br></p>\n                                                                ","rebloggedPostURL":"https://getbacktofandomlife.tumblr.com/post/719799014571343872/hannahbaker-make-me-choose-anon-asked-ravi"}]