[{"originalPostURL":"https://michaelcera.tumblr.com/post/146632691748","postBodyContent":"\n                                                                    <p></p><p><b><a href=\"http://michaelcera.tumblr.com/tagged/aes\">aesthetics</a><b> » the chronicles of narnia</b></b></p><blockquote><p><i><small>\n\nOnce a king or queen of Narnia, always a king or queen of Narnia.\n\n</small></i><br></p></blockquote>\n                                                                ","rebloggedPostURL":"https://getbacktofandomlife.tumblr.com/post/718336950021537792/michaelcera-aesthetics-the-chronicles-of"},{"originalPostURL":"https://scurviesdisneyblog.tumblr.com/post/164014223988","postBodyContent":"\n                                                                    <p>Moana and Gramma Tala by Annette Marnat (<a href=\"https://href.li/?http://www.fanpop.com/clubs/disneys-moana/images/40100646/title/moana-concept-art-photo\">x</a>)</p>\n                                                                ","rebloggedPostURL":"https://getbacktofandomlife.tumblr.com/post/718336943167094784/scurviesdisneyblog-moana-and-gramma-tala-by"},{"originalPostUsername":"","postBodyContent":"","rebloggedPostURL":"https://getbacktofandomlife.tumblr.com/post/718336938569023488"},{"originalPostURL":"https://artoo.tumblr.com/post/164336260281","postBodyContent":"\n                                                                        <p>if diego doesn’t at least have a cameo in the jabba movie, what is the point&nbsp;</p>\n                                                                    ","rebloggedPostURL":"https://getbacktofandomlife.tumblr.com/post/718336888847679488/artoo-lesbianrey-artoo-if-diego-doesnt-at"},{"originalPostURL":"https://jahcobperalta.tumblr.com/post/164154847853","postBodyContent":"\n                                                                    <p></p><blockquote><p><small><a href=\"http://jahcobperalta.tumblr.com/tagged/fcm\">favorite character meme</a> ≡ two colors: cyan (½)</small></p></blockquote>\n                                                                ","rebloggedPostURL":"https://getbacktofandomlife.tumblr.com/post/718336884571570176/jahcobperalta-favorite-character-meme-two"},{"originalPostURL":"https://dazeridley.tumblr.com/post/162420195819","postBodyContent":"\n                                                                    <p><b>❝ <i>Y</i></b><small>ou can kill me, but you will never destroy me. It takes strength to resist the dark side. Only the weak embrace it.</small> <b>❞ </b></p>\n                                                                ","rebloggedPostURL":"https://getbacktofandomlife.tumblr.com/post/718336854034874368/dazeridley-you-can-kill-me-but-you-will-never"},{"originalPostURL":"https://charlotteroleplays.tumblr.com/post/162767610935","postBodyContent":"\n                                                                    <p></p><blockquote><p><a href=\"https://href.li/?http://www.farfarawaysite.com/temple/i-j/jessicaparker/shoots1/gallery.htm\"><i>X.</i></a></p></blockquote>\n                                                                ","rebloggedPostURL":"https://getbacktofandomlife.tumblr.com/post/718336850461392896/charlotteroleplays-x"},{"originalPostURL":"https://starryeyesxx.tumblr.com/post/164266619933","postBodyContent":"\n                                                                    <p><i><b>{Buffyverse Dynamics: Spike &amp; Drusilla}</b></i><br></p>\n                                                                ","rebloggedPostURL":"https://getbacktofandomlife.tumblr.com/post/718336829753016320/starryeyesxx-buffyverse-dynamics-spike"},{"originalPostURL":"https://maximumstarks.tumblr.com/post/164263022641","postBodyContent":"\n                                                                    <p></p><blockquote><p><small><i>Working on a secret project, are we, Sir?</i></small></p></blockquote>\n                                                                ","rebloggedPostURL":"https://getbacktofandomlife.tumblr.com/post/718336821029978112/maximumstarks-working-on-a-secret-project-are"},{"originalPostUsername":"","postBodyContent":"","rebloggedPostURL":"https://getbacktofandomlife.tumblr.com/post/718336814956642304"}]