[{"originalPostURL":"https://trashcanprince.tumblr.com/post/166282737271","postBodyContent":"\n                                                                    <p>🌸🌸&nbsp;the yule ball&nbsp;🌸🌸</p>\n                                                                ","rebloggedPostURL":"https://getbacktofandomlife.tumblr.com/post/717425566246191104/savingharrypotter-trashcanprince-the-yule"},{"originalPostURL":"https://upthehillart.tumblr.com/post/145608882939","postBodyContent":"\n                                                                    <p><i>Regulus Black</i></p>\n                                                                ","rebloggedPostURL":"https://getbacktofandomlife.tumblr.com/post/717368433141071872/upthehillart-regulus-black"},{"originalPostURL":"https://declanlynch.tumblr.com/post/169323691342","postBodyContent":"\n                                                                    <p><sub>harry potter series: <b>james potter</b></sub></p>\n                                                                ","rebloggedPostURL":"https://getbacktofandomlife.tumblr.com/post/717343088402677760/declanlynch-harry-potter-series-james-potter"},{"originalPostURL":"https://sean-zevran.tumblr.com/post/169194166981","postBodyContent":"\n                                                                    <p></p><blockquote><p><i><small><b>Herein lies your truest strength. The energy of the demon. Its spirit. Its heart. </b>This is how you—<b>Created the Slayer? Yes.</b></small></i></p></blockquote>\n                                                                ","rebloggedPostURL":"https://getbacktofandomlife.tumblr.com/post/717343085692157952/sean-zevran-herein-lies-your-truest-strength-the"},{"originalPostUsername":"","postBodyContent":"","rebloggedPostURL":"https://getbacktofandomlife.tumblr.com/post/717343082977345536"},{"originalPostUsername":"","postBodyContent":"","rebloggedPostURL":"https://getbacktofandomlife.tumblr.com/post/717343080252145664"},{"originalPostURL":"https://neddstark.tumblr.com/post/166857559744","postBodyContent":"\n                                                                    <p><small><b>First Name:</b> <strike>FN-2187</strike> Finn<br><b>Last Name:</b> No Chill</small></p>\n                                                                ","rebloggedPostURL":"https://getbacktofandomlife.tumblr.com/post/717343077547802624/neddstark-first-name-fn-2187-finn-last-name-no"},{"originalPostURL":"https://perfectpalettes.tumblr.com/post/123778031457","postBodyContent":"\n                                                                    <p><small>EAC8CA |&nbsp;DFCED5 |&nbsp;D3D5DF</small></p>\n                                                                ","rebloggedPostURL":"https://getbacktofandomlife.tumblr.com/post/717343074835136512/perfectpalettes-eac8ca-dfced5-d3d5df"},{"originalPostUsername":"alrightanakin","postBodyContent":"\n                                                                        <p>“i hate alcohol” i say as i actively consume alcohol with the intention of acquiring more&nbsp;alcohol<br></p>\n                                                                    ","rebloggedPostURL":"https://getbacktofandomlife.tumblr.com/post/717343072128778240/alrightanakin-i-hate-alcohol-i-say-as-i"},{"originalPostURL":"https://persrephone.tumblr.com/post/149318367432","postBodyContent":"\n                                                                    <p></p><p><b><a href=\"http://persrephone.tumblr.com/tagged/character-posters\">character posters</a>:</b> Hermione Granger</p><blockquote><p><i>The brightest witch of her age.</i></p></blockquote>\n                                                                ","rebloggedPostURL":"https://getbacktofandomlife.tumblr.com/post/717343069441245184/persrephone-character-posters-hermione-granger"}]