[{"originalPostURL":"https://slaygal.tumblr.com/post/171218201049","postBodyContent":"\n                                                                    <p><a href=\"http://slaygal.tumblr.com/tagged/gifmeme\">gif meme</a>: dawn summers + showing emotion | requested by anonymous<br></p>\n                                                                ","rebloggedPostURL":"https://getbacktofandomlife.tumblr.com/post/716247306834477056/slaygal-gif-meme-dawn-summers-showing"},{"originalPostUsername":"","postBodyContent":"","rebloggedPostURL":"https://getbacktofandomlife.tumblr.com/post/716247304021131264"},{"originalPostURL":"https://lilli9.tumblr.com/post/172618130732","postBodyContent":"\n                                                                    <p>day to day</p>\n                                                                ","rebloggedPostURL":"https://getbacktofandomlife.tumblr.com/post/716247301332549632/lilli9-day-to-day"},{"originalPostURL":"https://milareadsbooks.tumblr.com/post/124063868705","postBodyContent":"\n                                                                        <p>“I Own It But I Haven’t&nbsp;Read It” a story by me<br></p>\n                                                                    ","rebloggedPostURL":"https://getbacktofandomlife.tumblr.com/post/716247298580054016/milareadsbooks-i-own-it-but-i-havent-read-it"},{"originalPostUsername":"faithslehane","postBodyContent":"\n                                                                    <p></p><p><a href=\"https://href.li/?denied:denied:%E2%80%9Chttp://www.faithslehane.tumblr.com/tagged/gtkm%E2%80%9D\"><b>get to know meme:</b></a> (1/5) tv shows - buffy the vampire slayer</p><i> the hardest thing in this world is to live in it. be brave. live.</i>\n                                                                ","rebloggedPostURL":"https://getbacktofandomlife.tumblr.com/post/716247295705972736/faithslehane-get-to-know-meme-15-tv-shows"},{"originalPostUsername":"chubbydeepmaroon","postBodyContent":"\n                                                                    <p>Clouds and smoke from the California wildfires this past weekend.&nbsp;<br><br>The sun and water had this weird sort’ve moment amidst sunset.</p>\n                                                                ","rebloggedPostURL":"https://getbacktofandomlife.tumblr.com/post/716247290864648192/chubbydeepmaroon-clouds-and-smoke-from-the"},{"originalPostURL":"https://dicaprios.tumblr.com/post/173544653586","postBodyContent":"\n                                                                    <p><small><a href=\"http://dicaprios.tumblr.com/tagged/iwontfinish\"><b>another meme that i won’t finish</b></a>:<b> </b>twelve characters \n— elizabeth ‘effy’ stonem.</small><br></p>\n                                                                ","rebloggedPostURL":"https://getbacktofandomlife.tumblr.com/post/716247253546860544/dicaprios-another-meme-that-i-wont-finish"},{"originalPostURL":"https://buckyssteves.tumblr.com/post/173492232887","postBodyContent":"\n                                                                    <p><i>#me when writing.</i></p>\n                                                                ","rebloggedPostURL":"https://getbacktofandomlife.tumblr.com/post/716247250101207040/buckyssteves-me-when-writing"},{"originalPostURL":"https://qinevra.tumblr.com/post/162707729927","postBodyContent":"\n                                                                    <p><b><i>hermione granger;</i></b> brightest witch of her age</p>\n                                                                ","rebloggedPostURL":"https://getbacktofandomlife.tumblr.com/post/716247246356742144/qinevra-hermione-granger-brightest-witch-of-her"},{"originalPostURL":"https://elvenking.tumblr.com/post/111759563237","postBodyContent":"\n                                                                    <p><small><small><b><a href=\"http://elveinking.tumblr.com/tagged/gif-request-meme\">GIF REQUEST MEME<br></a></b></small></small><small>∟ anonymous </small><small>asked Marvel +&nbsp;<i>favorite hero<br></i></small></p><blockquote><div><small>Tony Stark</small></div></blockquote>\n                                                                ","rebloggedPostURL":"https://getbacktofandomlife.tumblr.com/post/716247240758509568/elvenking-gif-request-meme-anonymous-asked"}]