[{"originalPostUsername":"","postBodyContent":"","rebloggedPostURL":"https://getbacktofandomlife.tumblr.com/post/719327494685196288"},{"originalPostURL":"https://vampireapologist.tumblr.com/post/154792145838","postBodyContent":"\n                                                                        <p>Being a good person is a choice. Don’t let people fool you into believing that truly good people never have bad thoughts, are never tempted by the easier path, by the low road, never mess up or act out selfishly. Never believe a person can be good without making a conscious effort.</p><p>Every single time you do something good, you’ve made a decision to make the world a little brighter.</p><p>Goodness is not an inherent trait, it is a choice. Keep making it! I see you, I’m proud of you, and I’m rooting for you!</p>\n                                                                    ","rebloggedPostURL":"https://getbacktofandomlife.tumblr.com/post/719327491990437888/vampireapologist-being-a-good-person-is-a"},{"originalPostUsername":"rosevtyler","postBodyContent":"\n                                                                    <p></p><p><small>character posters + <b><a href=\"http://rosevtyler.tumblr.com/tagged/doodles\">doodles</a></b></small></p><blockquote><p><small><i>“I am what I am, an’ I’m not ashamed.”</i><br></small></p></blockquote>\n                                                                ","rebloggedPostURL":"https://getbacktofandomlife.tumblr.com/post/719327487277056000/rosevtyler-character-posters-doodles-i-am"},{"originalPostURL":"https://hamiltonhell.tumblr.com/post/152176918822","postBodyContent":"\n                                                                    <p><a href=\"https://href.li/?http://www.pbs.org/wnet/gperf/episodes/hamiltons-america/\"><small>And when my prayers to god were met with indifference<br>I picked up a pen, I wrote my own deliverance!</small></a></p>\n                                                                ","rebloggedPostURL":"https://getbacktofandomlife.tumblr.com/post/719327484347334656/hamiltonhell-and-when-my-prayers-to-god-were-met"},{"originalPostURL":"https://cryingbabying.tumblr.com/post/154732854005","postBodyContent":"\n                                                                    <p></p><p><small><i><b>Melanie Martinez</b>&nbsp;+ discography as Instagram accounts</i></small></p><blockquote><p><small><i><a href=\"http://sunsetbabe.tumblr.com/post/151942767008/taylor-swift-album-eras-as-instagram-accounts\">insp.</a></i></small></p></blockquote>\n                                                                ","rebloggedPostURL":"https://getbacktofandomlife.tumblr.com/post/719327481157632000/cryingbabying-melanie-martinez-discography-as"},{"originalPostUsername":"","postBodyContent":"","rebloggedPostURL":"https://getbacktofandomlife.tumblr.com/post/719327478048571392"},{"originalPostURL":"https://angelandfaith.tumblr.com/post/155240657805","postBodyContent":"\n                                                                    <p></p><blockquote><p><sub><b>buffy/faith</b> + hands</sub></p></blockquote>\n                                                                ","rebloggedPostURL":"https://getbacktofandomlife.tumblr.com/post/719327475012861952/angelandfaith-buffyfaith-hands"},{"originalPostUsername":"","postBodyContent":"","rebloggedPostURL":"https://getbacktofandomlife.tumblr.com/post/719327465190866944"},{"originalPostURL":"https://alicelongbottom.tumblr.com/post/155056697515","postBodyContent":"\n                                                                    <p><small><i>There were relatives of their&nbsp;victims among the Hogwarts students, who now found themselves the unwilling objects of a gruesome sort of reflected fame as they walked the corridors: Susan Bones, whose uncle, aunt, and cousins had all died at the hands of one of the ten, said miserably during Herbology that she now had a good idea what it felt like to be Harry.</i></small><br></p>\n                                                                ","rebloggedPostURL":"https://getbacktofandomlife.tumblr.com/post/719327462325108736/alicelongbottom-there-were-relatives-of"},{"originalPostURL":"https://femslasharmy.tumblr.com/post/154917901585","postBodyContent":"\n                                                                    <p><small><b><a href=\"http://femslasharmy.tumblr.com/post/154266567755/femslash-challenge-meme\">1st femslash meme:</a></b> (¾) soft aesthetic wlw ships ~ Ginny Weasley ||| Luna Lovegood</small></p>\n                                                                ","rebloggedPostURL":"https://getbacktofandomlife.tumblr.com/post/719327458379415552/femslasharmy-1st-femslash-meme-%C2%BE-soft"}]