[{"originalPostUsername":"","postBodyContent":"","rebloggedPostURL":"https://getbacktofandomlife.tumblr.com/post/720161477418418176"},{"originalPostURL":"https://ahoyspn.tumblr.com/post/168185477776","postBodyContent":"\n                                                                    <p>#is either this or&nbsp;‘you’re the shortbus, shortbus’ there’s no between</p>\n                                                                ","rebloggedPostURL":"https://getbacktofandomlife.tumblr.com/post/720161474703753216/ahoyspn-is-either-this-or-youre-the-shortbus"},{"originalPostUsername":"","postBodyContent":"","rebloggedPostURL":"https://getbacktofandomlife.tumblr.com/post/720161471959580672"},{"originalPostURL":"https://thepunishergifs.tumblr.com/post/171137509524","postBodyContent":"\n                                                                    <p><small><i>“To thank you. You know, apology, whatever.”</i></small></p>\n                                                                ","rebloggedPostURL":"https://getbacktofandomlife.tumblr.com/post/720161469248012288/thepunishergifs-to-thank-you-you-know-apology"},{"originalPostURL":"https://bajn.tumblr.com/post/156417308126","postBodyContent":"\n                                                                        <p>me: says literally anything<br>\nme in my head: that was stupid and now everyone hates u. congrats</p>\n                                                                    ","rebloggedPostURL":"https://getbacktofandomlife.tumblr.com/post/720161466512261120/bajn-me-says-literally-anything-me-in-my-head"},{"originalPostURL":"https://watcherspet.tumblr.com/post/171634600898","postBodyContent":"\n                                                                    <p></p><blockquote><p>Buffy Summers + not interested in men’s bullshit</p></blockquote>\n                                                                ","rebloggedPostURL":"https://getbacktofandomlife.tumblr.com/post/720161463800561664/watcherspet-buffy-summers-not-interested-in"},{"originalPostURL":"https://jimminovak.tumblr.com/post/163867324533","postBodyContent":"\n                                                                    <p></p><blockquote><p><a href=\"http://jimminovak.tumblr.com/tagged/spn%20posters\">supernatural posters</a><b> \n\n→ </b><i>castiel</i></p><p><i><a href=\"http://jimminovak.tumblr.com/ask\">want one?</a></i></p></blockquote>\n                                                                ","rebloggedPostURL":"https://getbacktofandomlife.tumblr.com/post/720161461049212928/jimminovak-supernatural-posters-castiel"},{"originalPostURL":"https://00250.tumblr.com/post/126948598530","postBodyContent":"\n                                                                    <p></p><blockquote><div><small>(for <a href=\"http://iheartnewt.tumblr.com\">iheartnewt</a>) </small></div></blockquote>\n                                                                ","rebloggedPostURL":"https://getbacktofandomlife.tumblr.com/post/720161458345934848/00250for-iheartnewt"},{"originalPostURL":"https://neddstark.tumblr.com/post/170509696104","postBodyContent":"\n                                                                    <p><small>the man, the myth, the legend: Captain Raymond Holt</small></p>\n                                                                ","rebloggedPostURL":"https://getbacktofandomlife.tumblr.com/post/720161455624896513/neddstark-the-man-the-myth-the-legend-captain"},{"originalPostUsername":"","postBodyContent":"","rebloggedPostURL":"https://getbacktofandomlife.tumblr.com/post/720161452912263168"}]